kacypdf/__init__.py
kacypdf/pdf2text.py
kacypdf-1.0.dist-info/LICENSE
kacypdf-1.0.dist-info/METADATA
kacypdf-1.0.dist-info/WHEEL
kacypdf-1.0.dist-info/top_level.txt
kacypdf-1.0.dist-info/RECORD
